projecttimetracker-0.1.0.dist-info/RECORD
projecttimetracker-0.1.0.dist-info/DESCRIPTION.rst
projecttimetracker-0.1.0.dist-info/METADATA
projecttimetracker-0.1.0.dist-info/metadata.json
projecttimetracker-0.1.0.dist-info/entry_points.txt
projecttimetracker-0.1.0.dist-info/top_level.txt
projecttimetracker-0.1.0.dist-info/WHEEL
projecttimetracker/projecttimetracker.py
projecttimetracker/__init__.py
