Metadata-Version: 2.0
Name: projecttimetracker
Version: 0.1.0
Summary: CLI for easily tracking how much time you spend on each project
Home-page: https://github.com/reustonium/projecttimetracker
Author: Andy Ruestow
Author-email: andrew.ruestow@gmail.com
License: GPLv2
Keywords: projecttimetracker
Platform: UNKNOWN
Classifier: Development Status :: 2 - Pre-Alpha
Classifier: Intended Audience :: Developers
Classifier: License :: OSI Approved :: GNU General Public License v2 (GPLv2)
Classifier: Natural Language :: English
Classifier: Programming Language :: Python :: 2
Classifier: Programming Language :: Python :: 2.6
Classifier: Programming Language :: Python :: 2.7
Classifier: Programming Language :: Python :: 3
Classifier: Programming Language :: Python :: 3.3
Classifier: Programming Language :: Python :: 3.4
Requires-Dist: Click
